harpoon/__init__.py
harpoon/main.py
harpoon/commands/__init__.py
harpoon/commands/asn.py
harpoon/commands/base.py
harpoon/commands/binaryedge.py
harpoon/commands/censyscmd.py
harpoon/commands/certspotter.py
harpoon/commands/circl.py
harpoon/commands/config.py
harpoon/commands/crtsh.py
harpoon/commands/cybercure.py
harpoon/commands/dnsc.py
harpoon/commands/dnsdbcmd.py
harpoon/commands/githubcmd.py
harpoon/commands/gn.py
harpoon/commands/hashlookup.py
harpoon/commands/help.py
harpoon/commands/hibp.py
harpoon/commands/hunter.py
harpoon/commands/hybrid.py
harpoon/commands/intel.py
harpoon/commands/ip.py
harpoon/commands/ipinfo.py
harpoon/commands/koodousc.py
harpoon/commands/malshare.py
harpoon/commands/misp.py
harpoon/commands/numverify.py
harpoon/commands/opencage.py
harpoon/commands/otx.py
harpoon/commands/permacc.py
harpoon/commands/pgp.py
harpoon/commands/phishtank.py
harpoon/commands/pithus.py
harpoon/commands/pt.py
harpoon/commands/pulsedive.py
harpoon/commands/quad9.py
harpoon/commands/robtex.py
harpoon/commands/safebrowsing.py
harpoon/commands/save.py
harpoon/commands/sectrailscmd.py
harpoon/commands/shodancmd.py
harpoon/commands/spyonwebcmd.py
harpoon/commands/subdomains.py
harpoon/commands/telegram.py
harpoon/commands/threatcrowd.py
harpoon/commands/threatgrid.py
harpoon/commands/threatminerc.py
harpoon/commands/tor.py
harpoon/commands/twitter.py
harpoon/commands/umbrella.py
harpoon/commands/update.py
harpoon/commands/urlhaus.py
harpoon/commands/urlscan.py
harpoon/commands/vt.py
harpoon/commands/xforce.py
harpoon/commands/zetalyticsc.py
harpoon/data/caida.txt
harpoon/data/example.conf
harpoon/lib/__init__.py
harpoon/lib/archiveis.py
harpoon/lib/archiveorg.py
harpoon/lib/bird.py
harpoon/lib/certspotter.py
harpoon/lib/cybercure.py
harpoon/lib/dnsdb.py
harpoon/lib/hibp.py
harpoon/lib/hybrid.py
harpoon/lib/ipinfo.py
harpoon/lib/koodous.py
harpoon/lib/malshare.py
harpoon/lib/memento.py
harpoon/lib/opencage.py
harpoon/lib/pgp.py
harpoon/lib/phishtank.py
harpoon-0.1.7.dist-info/LICENSE
harpoon-0.1.7.dist-info/METADATA
harpoon-0.1.7.dist-info/WHEEL
harpoon-0.1.7.dist-info/entry_points.txt
harpoon-0.1.7.dist-info/top_level.txt
harpoon-0.1.7.dist-info/RECORD
