Metadata-Version: 2.1
Name: harpoon
Version: 0.1.7
Summary: Another OSINT CLI tool
Home-page: https://github.com/Te-k/harpoon
Author: Tek
Author-email: tek@randhome.io
License: GPLv3
Keywords: osint threatintel
Platform: UNKNOWN
Classifier: Programming Language :: Python :: 3
Classifier: License :: OSI Approved :: MIT License
Classifier: Operating System :: OS Independent
Requires-Python: >=3.5
License-File: LICENSE
Requires-Dist: requests
Requires-Dist: configparser
Requires-Dist: tweepy (>=3.8.0)
Requires-Dist: passivetotal (>=2.5.9)
Requires-Dist: beautifulsoup4 (==4.11.1)
Requires-Dist: lxml (==4.9.1)
Requires-Dist: censys (==2.0.9)
Requires-Dist: shodan
Requires-Dist: fullcontact.py
Requires-Dist: pyhunter
Requires-Dist: PyGitHub (>=1.55)
Requires-Dist: telethon (==0.19.1.6)
Requires-Dist: virustotal-api
Requires-Dist: pymisp (==2.4.159)
Requires-Dist: OTXv2
Requires-Dist: IPy
Requires-Dist: maxminddb (>=1.4.0)
Requires-Dist: pyasn
Requires-Dist: spyonweb (==0.1)
Requires-Dist: selenium
Requires-Dist: geoip2
Requires-Dist: dnspython
Requires-Dist: consolemd (==0.5.1)
Requires-Dist: pypermacc (==0.1.1)
Requires-Dist: archiveis
Requires-Dist: pytz
Requires-Dist: pypdns (==1.3)
Requires-Dist: pybinaryedge (==0.5)
Requires-Dist: pythreatgrid2 (==0.1.1)
Requires-Dist: pycrtsh (==0.3.10)
Requires-Dist: pysafebrowsing (==0.1.2)
Requires-Dist: pysecuritytrails (==0.1.3)
Requires-Dist: phonenumbers (==8.12.4)
Requires-Dist: threatminer (==1.0)
Requires-Dist: zetalytics-api (==1.0.1)
Requires-Dist: greynoise (>=1.2.0)
Requires-Dist: pyhashlookup (==1.1.1)
Requires-Dist: simplejson (==3.17.6)
